regression_model/VERSION
regression_model/__init__.py
regression_model/config.yml
regression_model/pipeline.py
regression_model/predict.py
regression_model/train_pipeline.py
regression_model/config/__init__.py
regression_model/config/core.py
regression_model/datasets/__init__.py
regression_model/datasets/test.csv
regression_model/datasets/train.csv
regression_model/processing/__init__.py
regression_model/processing/data_manager.py
regression_model/processing/features.py
regression_model/processing/validation.py
regression_model/trained_model/__init__.py
regression_model/trained_model/regression_model_output_v0.0.2.pkl
sin_hdb_resale_price_regression_model-0.0.2.dist-info/METADATA
sin_hdb_resale_price_regression_model-0.0.2.dist-info/WHEEL
sin_hdb_resale_price_regression_model-0.0.2.dist-info/top_level.txt
sin_hdb_resale_price_regression_model-0.0.2.dist-info/RECORD
